certbot_dns_cloudflare_cname/__init__.py
certbot_dns_cloudflare_cname/py.typed
certbot_dns_cloudflare_cname/_internal/__init__.py
certbot_dns_cloudflare_cname/_internal/dns_cloudflare_cname.py
certbot_dns_cloudflare_cname-1.0.1.dist-info/LICENSE.txt
certbot_dns_cloudflare_cname-1.0.1.dist-info/METADATA
certbot_dns_cloudflare_cname-1.0.1.dist-info/WHEEL
certbot_dns_cloudflare_cname-1.0.1.dist-info/entry_points.txt
certbot_dns_cloudflare_cname-1.0.1.dist-info/top_level.txt
certbot_dns_cloudflare_cname-1.0.1.dist-info/RECORD
