Metadata-Version: 2.1
Name: certbot-dns-cloudflare-cname
Version: 1.0.1
Summary: Cloudflare DNS Authenticator plugin for Certbot with CNAME support.
Home-page: https://github.com/rsc-dev/certbot-dns-cloudflare-cname
Author: Radoslaw Matusiak
Author-email: radoslaw.matusiak@gmail.com
License: Apache License 2.0
Classifier: Development Status :: 5 - Production/Stable
Classifier: Environment :: Plugins
Classifier: Intended Audience :: System Administrators
Classifier: License :: OSI Approved :: Apache Software License
Classifier: Operating System :: POSIX :: Linux
Classifier: Programming Language :: Python
Classifier: Programming Language :: Python :: 3
Classifier: Programming Language :: Python :: 3.7
Classifier: Programming Language :: Python :: 3.8
Classifier: Programming Language :: Python :: 3.9
Classifier: Programming Language :: Python :: 3.10
Classifier: Topic :: Internet :: WWW/HTTP
Classifier: Topic :: Security
Classifier: Topic :: System :: Installation/Setup
Classifier: Topic :: System :: Networking
Classifier: Topic :: System :: Systems Administration
Classifier: Topic :: Utilities
Requires-Python: >=3.7
License-File: LICENSE.txt
Requires-Dist: cloudflare (>=1.5.1)
Requires-Dist: setuptools (>=41.6.0)
Requires-Dist: dnspython (>=2.2.0)
Requires-Dist: acme (>=1.0.1)
Requires-Dist: certbot (>=1.0.1)
